kandji/__init__.py
kandji/kandji.py
kandji-0.1.0.dist-info/LICENSE
kandji-0.1.0.dist-info/WHEEL
kandji-0.1.0.dist-info/METADATA
kandji-0.1.0.dist-info/RECORD
