Metadata-Version: 2.1
Name: kandji
Version: 0.1.0
Summary: A python wrapper for the Kandji API
Home-page: https://github.com/frefrik/python-kandji
License: MIT
Keywords: kandji,api,wrapper,python
Author: Fredrik Haarstad
Author-email: codemonkey@zomg.no
Requires-Python: >=3.8,<4.0
Classifier: License :: OSI Approved :: MIT License
Classifier: Programming Language :: Python :: 3
Classifier: Programming Language :: Python :: 3.10
Classifier: Programming Language :: Python :: 3.8
Classifier: Programming Language :: Python :: 3.9
Requires-Dist: requests (>=2.28.1,<3.0.0)
Project-URL: Repository, https://github.com/frefrik/python-kandji
